mq_client.py
mq_listener.py
mq_publisher.py
setup.py
mq_client.egg-info/PKG-INFO
mq_client.egg-info/SOURCES.txt
mq_client.egg-info/dependency_links.txt
mq_client.egg-info/entry_points.txt
mq_client.egg-info/requires.txt
mq_client.egg-info/top_level.txt