Metadata-Version: 1.0
Name: mq-client
Version: 0.0.3.7
Summary: A simple pika client implementation based on the examples.
Home-page: https://github.com/deginner/mq-client
Author: deginner
Author-email: support@deginner.com
License: UNKNOWN
Platform: UNKNOWN
